parpar/__init__.py
parpar/parpar.py
parpar/utils.py
parpar-0.0.19.dist-info/LICENSE
parpar-0.0.19.dist-info/METADATA
parpar-0.0.19.dist-info/WHEEL
parpar-0.0.19.dist-info/top_level.txt
parpar-0.0.19.dist-info/RECORD
