Metadata-Version: 2.1
Name: parpar
Version: 0.0.19
Summary: Parallel parser for large files
Home-page: https://pypi.org/project/parpar/
Author: Sumner Magruder
Author-email: sumner.magruder@zmnh.uni-hamburg.de
License: UNKNOWN
Platform: UNKNOWN
Classifier: Programming Language :: Python :: 3.5
Classifier: License :: OSI Approved :: MIT License
Classifier: Operating System :: OS Independent
